libdeye/__init__.py
libdeye/cli.py
libdeye/cloud_api.py
libdeye/const.py
libdeye/device_command.py
libdeye/device_state.py
libdeye/mqtt_client.py
libdeye/py.typed
libdeye-2.1.3.dist-info/licenses/LICENSE.txt
libdeye-2.1.3.dist-info/METADATA
libdeye-2.1.3.dist-info/WHEEL
libdeye-2.1.3.dist-info/entry_points.txt
libdeye-2.1.3.dist-info/top_level.txt
libdeye-2.1.3.dist-info/RECORD
