Metadata-Version: 2.4
Name: libdeye
Version: 2.1.3
Summary: A Python library to connect to Deye Cloud (德业云) and control Deye (德业) dehumidifier/humidifier devices.
Home-page: https://github.com/stackia/libdeye/
Author: Stackie Jia
Author-email: jsq2627@gmail.com
License: MIT
Project-URL: Source, https://github.com/stackia/libdeye/
Project-URL: Changelog, https://libdeye.readthedocs.io/en/latest/changelog.html
Project-URL: Tracker, https://github.com/stackia/libdeye/issues
Platform: any
Classifier: Development Status :: 5 - Production/Stable
Classifier: Programming Language :: Python
Classifier: Topic :: Home Automation
Requires-Python: >=3.10
License-File: LICENSE.txt
Requires-Dist: aiohttp<4.0,>=3.8
Requires-Dist: PyJWT<3.0,>=2.0
Requires-Dist: paho-mqtt<3,>=1.6
Provides-Extra: dev
Requires-Dist: setuptools; extra == "dev"
Requires-Dist: pytest; extra == "dev"
Requires-Dist: pytest-cov; extra == "dev"
Requires-Dist: aioresponses; extra == "dev"
Requires-Dist: pytest-asyncio; extra == "dev"
Requires-Dist: pre-commit; extra == "dev"
Requires-Dist: mypy; extra == "dev"
Dynamic: license-file
